{"start_time": 1671114871079, "received_packet_list": [{"packet_id": "0", "received_time": 1671114877899}, {"packet_id": "1", "received_time": 1671114877909}, {"packet_id": "21", "received_time": 1671114877924}, {"packet_id": "107", "received_time": 1671114877944}, {"packet_id": "108", "received_time": 1671114877963}, {"packet_id": "312", "received_time": 1671114877973}, {"packet_id": "685", "received_time": 1671114877979}, {"packet_id": "1039", "received_time": 1671114877997}, {"packet_id": "1117", "received_time": 1671114878021}, {"packet_id": "1118", "received_time": 1671114878032}, {"packet_id": "1119", "received_time": 1671114878036}, {"packet_id": "1329", "received_time": 1671114878040}, {"packet_id": "1545", "received_time": 1671114878045}, {"packet_id": "1587", "received_time": 1671114878050}, {"packet_id": "1633", "received_time": 1671114878063}, {"packet_id": "1702", "received_time": 1671114878072}, {"packet_id": "1886", "received_time": 1671114878091}, {"packet_id": "1965", "received_time": 1671114878102}, {"packet_id": "2046", "received_time": 1671114878108}, {"packet_id": "2453", "received_time": 1671114878114}, {"packet_id": "2559", "received_time": 1671114878124}, {"packet_id": "2629", "received_time": 1671114878145}, {"packet_id": "2739", "received_time": 1671114878169}, {"packet_id": "2816", "received_time": 1671114878177}, {"packet_id": "3112", "received_time": 1671114878181}, {"packet_id": "3164", "received_time": 1671114878187}, {"packet_id": "3250", "received_time": 1671114878193}, {"packet_id": "3338", "received_time": 1671114878200}, {"packet_id": "3409", "received_time": 1671114878204}, {"packet_id": "3499", "received_time": 1671114878209}, {"packet_id": "3592", "received_time": 1671114878235}, {"packet_id": "3663", "received_time": 1671114878255}, {"packet_id": "3710", "received_time": 1671114878266}, {"packet_id": "4181", "received_time": 1671114878274}, {"packet_id": "4567", "received_time": 1671114878290}, {"packet_id": "4659", "received_time": 1671114878308}, {"packet_id": "4725", "received_time": 1671114878326}, {"packet_id": "4828", "received_time": 1671114878330}, {"packet_id": "4996", "received_time": 1671114878336}, {"packet_id": "5118", "received_time": 1671114878340}, {"packet_id": "5119", "received_time": 1671114878345}, {"packet_id": "5191", "received_time": 1671114878350}, {"packet_id": "5243", "received_time": 1671114878358}, {"packet_id": "5295", "received_time": 1671114878367}, {"packet_id": "5384", "received_time": 1671114878373}, {"packet_id": "5465", "received_time": 1671114878383}, {"packet_id": "5572", "received_time": 1671114878389}, {"packet_id": "5573", "received_time": 1671114878393}, {"packet_id": "5651", "received_time": 1671114878400}, {"packet_id": "5708", "received_time": 1671114878420}, {"packet_id": "5709", "received_time": 1671114878465}, {"packet_id": "5780", "received_time": 1671114878523}, {"packet_id": "5826", "received_time": 1671114878844}, {"packet_id": "6369", "received_time": 1671114878860}, {"packet_id": "7207", "received_time": 1671114878874}, {"packet_id": "7742", "received_time": 1671114878894}, {"packet_id": "14498", "received_time": 1671114879158}, {"packet_id": "14665", "received_time": 1671114879228}, {"packet_id": "14868", "received_time": 1671114879284}, {"packet_id": "20257", "received_time": 1671114879312}, {"packet_id": "21215", "received_time": 1671114879336}, {"packet_id": "22330", "received_time": 1671114879341}, {"packet_id": "22677", "received_time": 1671114879372}, {"packet_id": "23101", "received_time": 1671114879384}, {"packet_id": "23167", "received_time": 1671114879638}, {"packet_id": "23720", "received_time": 1671114879919}, {"packet_id": "23839", "received_time": 1671114880156}, {"packet_id": "23992", "received_time": 1671114880166}]}