{
  "start_time": 1669300197273,
  "received_packet_list": [
    {
      "packet_id": "45",
      "received_time": 1669300197303
    },
    {
      "packet_id": "46",
      "received_time": 1669300197412
    },
    {
      "packet_id": "47",
      "received_time": 1669300197524
    },
    {
      "packet_id": "48",
      "received_time": 1669300197633
    },
    {
      "packet_id": "49",
      "received_time": 1669300197740
    },
    {
      "packet_id": "50",
      "received_time": 1669300197848
    },
    {
      "packet_id": "51",
      "received_time": 1669300197958
    },
    {
      "packet_id": "52",
      "received_time": 1669300198065
    },
    {
      "packet_id": "53",
      "received_time": 1669300198174
    },
    {
      "packet_id": "54",
      "received_time": 1669300198284
    },
    {
      "packet_id": "55",
      "received_time": 1669300198395
    },
    {
      "packet_id": "56",
      "received_time": 1669300198501
    },
    {
      "packet_id": "57",
      "received_time": 1669300198612
    },
    {
      "packet_id": "58",
      "received_time": 1669300198722
    },
    {
      "packet_id": "59",
      "received_time": 1669300198832
    },
    {
      "packet_id": "60",
      "received_time": 1669300198941
    },
    {
      "packet_id": "61",
      "received_time": 1669300199049
    },
    {
      "packet_id": "62",
      "received_time": 1669300199159
    },
    {
      "packet_id": "63",
      "received_time": 1669300199268
    },
    {
      "packet_id": "64",
      "received_time": 1669300199378
    },
    {
      "packet_id": "65",
      "received_time": 1669300199488
    },
    {
      "packet_id": "66",
      "received_time": 1669300199599
    },
    {
      "packet_id": "67",
      "received_time": 1669300199708
    },
    {
      "packet_id": "68",
      "received_time": 1669300199815
    },
    {
      "packet_id": "69",
      "received_time": 1669300199924
    },
    {
      "packet_id": "70",
      "received_time": 1669300200034
    },
    {
      "packet_id": "71",
      "received_time": 1669300200143
    },
    {
      "packet_id": "72",
      "received_time": 1669300200253
    },
    {
      "packet_id": "73",
      "received_time": 1669300200362
    },
    {
      "packet_id": "74",
      "received_time": 1669300200470
    },
    {
      "packet_id": "75",
      "received_time": 1669300200579
    },
    {
      "packet_id": "76",
      "received_time": 1669300200689
    },
    {
      "packet_id": "77",
      "received_time": 1669300200797
    },
    {
      "packet_id": "78",
      "received_time": 1669300200907
    },
    {
      "packet_id": "79",
      "received_time": 1669300201017
    },
    {
      "packet_id": "80",
      "received_time": 1669300201128
    },
    {
      "packet_id": "81",
      "received_time": 1669300201239
    },
    {
      "packet_id": "82",
      "received_time": 1669300201348
    },
    {
      "packet_id": "83",
      "received_time": 1669300201458
    },
    {
      "packet_id": "84",
      "received_time": 1669300201566
    },
    {
      "packet_id": "85",
      "received_time": 1669300201676
    },
    {
      "packet_id": "86",
      "received_time": 1669300201785
    },
    {
      "packet_id": "87",
      "received_time": 1669300201893
    },
    {
      "packet_id": "88",
      "received_time": 1669300202000
    },
    {
      "packet_id": "89",
      "received_time": 1669300202104
    },
    {
      "packet_id": "90",
      "received_time": 1669300202214
    },
    {
      "packet_id": "91",
      "received_time": 1669300202323
    },
    {
      "packet_id": "92",
      "received_time": 1669300202432
    },
    {
      "packet_id": "93",
      "received_time": 1669300202541
    },
    {
      "packet_id": "94",
      "received_time": 1669300202649
    },
    {
      "packet_id": "95",
      "received_time": 1669300202760
    },
    {
      "packet_id": "96",
      "received_time": 1669300202868
    },
    {
      "packet_id": "97",
      "received_time": 1669300202978
    },
    {
      "packet_id": "98",
      "received_time": 1669300203086
    },
    {
      "packet_id": "99",
      "received_time": 1669300203195
    },
    {
      "packet_id": "100",
      "received_time": 1669300203303
    },
    {
      "packet_id": "101",
      "received_time": 1669300203413
    },
    {
      "packet_id": "102",
      "received_time": 1669300203523
    },
    {
      "packet_id": "103",
      "received_time": 1669300203632
    },
    {
      "packet_id": "104",
      "received_time": 1669300203742
    },
    {
      "packet_id": "105",
      "received_time": 1669300203852
    },
    {
      "packet_id": "106",
      "received_time": 1669300203961
    },
    {
      "packet_id": "107",
      "received_time": 1669300204070
    },
    {
      "packet_id": "108",
      "received_time": 1669300204180
    },
    {
      "packet_id": "109",
      "received_time": 1669300204289
    },
    {
      "packet_id": "110",
      "received_time": 1669300204398
    },
    {
      "packet_id": "111",
      "received_time": 1669300204507
    },
    {
      "packet_id": "112",
      "received_time": 1669300204616
    },
    {
      "packet_id": "113",
      "received_time": 1669300204726
    },
    {
      "packet_id": "114",
      "received_time": 1669300204836
    },
    {
      "packet_id": "115",
      "received_time": 1669300204944
    },
    {
      "packet_id": "116",
      "received_time": 1669300205054
    },
    {
      "packet_id": "117",
      "received_time": 1669300205164
    },
    {
      "packet_id": "118",
      "received_time": 1669300205273
    },
    {
      "packet_id": "119",
      "received_time": 1669300205382
    },
    {
      "packet_id": "120",
      "received_time": 1669300205494
    },
    {
      "packet_id": "121",
      "received_time": 1669300205603
    },
    {
      "packet_id": "122",
      "received_time": 1669300205713
    },
    {
      "packet_id": "123",
      "received_time": 1669300205823
    },
    {
      "packet_id": "124",
      "received_time": 1669300205932
    },
    {
      "packet_id": "125",
      "received_time": 1669300206042
    },
    {
      "packet_id": "126",
      "received_time": 1669300206152
    },
    {
      "packet_id": "127",
      "received_time": 1669300206261
    },
    {
      "packet_id": "128",
      "received_time": 1669300206371
    },
    {
      "packet_id": "129",
      "received_time": 1669300206480
    },
    {
      "packet_id": "130",
      "received_time": 1669300206590
    },
    {
      "packet_id": "131",
      "received_time": 1669300206700
    },
    {
      "packet_id": "132",
      "received_time": 1669300206809
    },
    {
      "packet_id": "133",
      "received_time": 1669300206919
    },
    {
      "packet_id": "134",
      "received_time": 1669300207029
    },
    {
      "packet_id": "135",
      "received_time": 1669300207139
    },
    {
      "packet_id": "136",
      "received_time": 1669300207249
    },
    {
      "packet_id": "137",
      "received_time": 1669300207359
    },
    {
      "packet_id": "138",
      "received_time": 1669300207467
    },
    {
      "packet_id": "139",
      "received_time": 1669300207575
    },
    {
      "packet_id": "140",
      "received_time": 1669300207686
    },
    {
      "packet_id": "141",
      "received_time": 1669300207796
    },
    {
      "packet_id": "142",
      "received_time": 1669300207907
    },
    {
      "packet_id": "143",
      "received_time": 1669300208019
    },
    {
      "packet_id": "144",
      "received_time": 1669300208130
    },
    {
      "packet_id": "145",
      "received_time": 1669300208239
    },
    {
      "packet_id": "146",
      "received_time": 1669300208349
    },
    {
      "packet_id": "147",
      "received_time": 1669300208459
    },
    {
      "packet_id": "148",
      "received_time": 1669300208566
    },
    {
      "packet_id": "149",
      "received_time": 1669300208676
    },
    {
      "packet_id": "150",
      "received_time": 1669300208787
    },
    {
      "packet_id": "151",
      "received_time": 1669300208895
    },
    {
      "packet_id": "152",
      "received_time": 1669300209006
    },
    {
      "packet_id": "153",
      "received_time": 1669300209116
    },
    {
      "packet_id": "154",
      "received_time": 1669300209228
    },
    {
      "packet_id": "155",
      "received_time": 1669300209339
    },
    {
      "packet_id": "156",
      "received_time": 1669300209450
    },
    {
      "packet_id": "157",
      "received_time": 1669300209558
    },
    {
      "packet_id": "158",
      "received_time": 1669300209666
    },
    {
      "packet_id": "159",
      "received_time": 1669300209774
    },
    {
      "packet_id": "160",
      "received_time": 1669300209884
    },
    {
      "packet_id": "161",
      "received_time": 1669300209995
    },
    {
      "packet_id": "162",
      "received_time": 1669300210104
    },
    {
      "packet_id": "163",
      "received_time": 1669300210214
    },
    {
      "packet_id": "164",
      "received_time": 1669300210322
    },
    {
      "packet_id": "165",
      "received_time": 1669300210430
    },
    {
      "packet_id": "166",
      "received_time": 1669300210540
    },
    {
      "packet_id": "167",
      "received_time": 1669300210649
    },
    {
      "packet_id": "168",
      "received_time": 1669300210761
    },
    {
      "packet_id": "169",
      "received_time": 1669300210871
    },
    {
      "packet_id": "170",
      "received_time": 1669300210982
    },
    {
      "packet_id": "171",
      "received_time": 1669300211094
    },
    {
      "packet_id": "172",
      "received_time": 1669300211202
    },
    {
      "packet_id": "173",
      "received_time": 1669300211314
    },
    {
      "packet_id": "174",
      "received_time": 1669300211422
    },
    {
      "packet_id": "175",
      "received_time": 1669300211530
    },
    {
      "packet_id": "176",
      "received_time": 1669300211640
    },
    {
      "packet_id": "177",
      "received_time": 1669300211749
    },
    {
      "packet_id": "178",
      "received_time": 1669300211858
    },
    {
      "packet_id": "179",
      "received_time": 1669300211969
    },
    {
      "packet_id": "180",
      "received_time": 1669300212080
    },
    {
      "packet_id": "181",
      "received_time": 1669300212189
    },
    {
      "packet_id": "182",
      "received_time": 1669300212298
    },
    {
      "packet_id": "183",
      "received_time": 1669300212407
    },
    {
      "packet_id": "184",
      "received_time": 1669300212519
    },
    {
      "packet_id": "185",
      "received_time": 1669300212630
    },
    {
      "packet_id": "186",
      "received_time": 1669300212736
    },
    {
      "packet_id": "187",
      "received_time": 1669300212847
    },
    {
      "packet_id": "188",
      "received_time": 1669300212956
    },
    {
      "packet_id": "189",
      "received_time": 1669300213068
    },
    {
      "packet_id": "190",
      "received_time": 1669300213176
    },
    {
      "packet_id": "191",
      "received_time": 1669300213285
    },
    {
      "packet_id": "192",
      "received_time": 1669300213396
    },
    {
      "packet_id": "193",
      "received_time": 1669300213504
    },
    {
      "packet_id": "194",
      "received_time": 1669300213614
    },
    {
      "packet_id": "195",
      "received_time": 1669300213726
    },
    {
      "packet_id": "196",
      "received_time": 1669300213835
    },
    {
      "packet_id": "197",
      "received_time": 1669300213943
    },
    {
      "packet_id": "198",
      "received_time": 1669300214052
    },
    {
      "packet_id": "199",
      "received_time": 1669300214160
    },
    {
      "packet_id": "200",
      "received_time": 1669300214271
    },
    {
      "packet_id": "201",
      "received_time": 1669300214382
    },
    {
      "packet_id": "202",
      "received_time": 1669300214492
    },
    {
      "packet_id": "203",
      "received_time": 1669300214602
    },
    {
      "packet_id": "204",
      "received_time": 1669300214712
    },
    {
      "packet_id": "205",
      "received_time": 1669300214821
    },
    {
      "packet_id": "206",
      "received_time": 1669300214929
    },
    {
      "packet_id": "207",
      "received_time": 1669300215039
    },
    {
      "packet_id": "208",
      "received_time": 1669300215147
    },
    {
      "packet_id": "209",
      "received_time": 1669300215257
    },
    {
      "packet_id": "210",
      "received_time": 1669300215366
    },
    {
      "packet_id": "211",
      "received_time": 1669300215475
    },
    {
      "packet_id": "212",
      "received_time": 1669300215586
    },
    {
      "packet_id": "213",
      "received_time": 1669300215696
    },
    {
      "packet_id": "214",
      "received_time": 1669300215804
    },
    {
      "packet_id": "215",
      "received_time": 1669300215914
    },
    {
      "packet_id": "216",
      "received_time": 1669300216026
    },
    {
      "packet_id": "217",
      "received_time": 1669300216138
    },
    {
      "packet_id": "218",
      "received_time": 1669300216250
    },
    {
      "packet_id": "219",
      "received_time": 1669300216361
    },
    {
      "packet_id": "220",
      "received_time": 1669300216473
    },
    {
      "packet_id": "221",
      "received_time": 1669300216585
    },
    {
      "packet_id": "222",
      "received_time": 1669300216697
    },
    {
      "packet_id": "223",
      "received_time": 1669300216808
    },
    {
      "packet_id": "224",
      "received_time": 1669300216918
    },
    {
      "packet_id": "225",
      "received_time": 1669300217028
    },
    {
      "packet_id": "226",
      "received_time": 1669300217138
    },
    {
      "packet_id": "227",
      "received_time": 1669300217247
    },
    {
      "packet_id": "228",
      "received_time": 1669300217359
    },
    {
      "packet_id": "229",
      "received_time": 1669300217470
    },
    {
      "packet_id": "230",
      "received_time": 1669300217582
    },
    {
      "packet_id": "231",
      "received_time": 1669300217694
    },
    {
      "packet_id": "232",
      "received_time": 1669300217806
    },
    {
      "packet_id": "233",
      "received_time": 1669300217918
    },
    {
      "packet_id": "234",
      "received_time": 1669300218027
    },
    {
      "packet_id": "235",
      "received_time": 1669300218137
    },
    {
      "packet_id": "236",
      "received_time": 1669300218248
    },
    {
      "packet_id": "237",
      "received_time": 1669300218360
    },
    {
      "packet_id": "238",
      "received_time": 1669300218471
    },
    {
      "packet_id": "239",
      "received_time": 1669300218583
    },
    {
      "packet_id": "240",
      "received_time": 1669300218695
    },
    {
      "packet_id": "241",
      "received_time": 1669300218807
    },
    {
      "packet_id": "242",
      "received_time": 1669300218918
    },
    {
      "packet_id": "243",
      "received_time": 1669300219028
    },
    {
      "packet_id": "244",
      "received_time": 1669300219140
    },
    {
      "packet_id": "245",
      "received_time": 1669300219252
    },
    {
      "packet_id": "246",
      "received_time": 1669300219363
    },
    {
      "packet_id": "247",
      "received_time": 1669300219475
    },
    {
      "packet_id": "248",
      "received_time": 1669300219587
    },
    {
      "packet_id": "249",
      "received_time": 1669300219699
    },
    {
      "packet_id": "250",
      "received_time": 1669300219810
    },
    {
      "packet_id": "251",
      "received_time": 1669300219922
    },
    {
      "packet_id": "252",
      "received_time": 1669300220034
    },
    {
      "packet_id": "253",
      "received_time": 1669300220146
    },
    {
      "packet_id": "254",
      "received_time": 1669300220257
    },
    {
      "packet_id": "255",
      "received_time": 1669300220368
    },
    {
      "packet_id": "256",
      "received_time": 1669300220480
    },
    {
      "packet_id": "257",
      "received_time": 1669300220592
    },
    {
      "packet_id": "258",
      "received_time": 1669300220701
    },
    {
      "packet_id": "259",
      "received_time": 1669300220813
    },
    {
      "packet_id": "260",
      "received_time": 1669300220924
    },
    {
      "packet_id": "261",
      "received_time": 1669300221036
    },
    {
      "packet_id": "262",
      "received_time": 1669300221145
    },
    {
      "packet_id": "263",
      "received_time": 1669300221256
    },
    {
      "packet_id": "264",
      "received_time": 1669300221367
    },
    {
      "packet_id": "265",
      "received_time": 1669300221479
    },
    {
      "packet_id": "266",
      "received_time": 1669300221591
    },
    {
      "packet_id": "267",
      "received_time": 1669300221702
    },
    {
      "packet_id": "268",
      "received_time": 1669300221814
    },
    {
      "packet_id": "269",
      "received_time": 1669300221925
    },
    {
      "packet_id": "270",
      "received_time": 1669300222037
    },
    {
      "packet_id": "271",
      "received_time": 1669300222147
    },
    {
      "packet_id": "272",
      "received_time": 1669300222257
    },
    {
      "packet_id": "273",
      "received_time": 1669300222366
    },
    {
      "packet_id": "274",
      "received_time": 1669300222477
    },
    {
      "packet_id": "275",
      "received_time": 1669300222588
    },
    {
      "packet_id": "276",
      "received_time": 1669300222697
    },
    {
      "packet_id": "277",
      "received_time": 1669300222808
    },
    {
      "packet_id": "278",
      "received_time": 1669300222918
    },
    {
      "packet_id": "279",
      "received_time": 1669300223028
    },
    {
      "packet_id": "280",
      "received_time": 1669300223136
    },
    {
      "packet_id": "281",
      "received_time": 1669300223247
    },
    {
      "packet_id": "282",
      "received_time": 1669300223358
    },
    {
      "packet_id": "283",
      "received_time": 1669300223468
    },
    {
      "packet_id": "284",
      "received_time": 1669300223579
    },
    {
      "packet_id": "285",
      "received_time": 1669300223686
    },
    {
      "packet_id": "286",
      "received_time": 1669300223795
    },
    {
      "packet_id": "287",
      "received_time": 1669300223904
    },
    {
      "packet_id": "288",
      "received_time": 1669300224013
    },
    {
      "packet_id": "289",
      "received_time": 1669300224124
    },
    {
      "packet_id": "290",
      "received_time": 1669300224234
    },
    {
      "packet_id": "291",
      "received_time": 1669300224343
    },
    {
      "packet_id": "292",
      "received_time": 1669300224452
    },
    {
      "packet_id": "293",
      "received_time": 1669300224561
    },
    {
      "packet_id": "294",
      "received_time": 1669300224671
    },
    {
      "packet_id": "295",
      "received_time": 1669300224779
    },
    {
      "packet_id": "296",
      "received_time": 1669300224889
    },
    {
      "packet_id": "297",
      "received_time": 1669300224999
    },
    {
      "packet_id": "298",
      "received_time": 1669300225106
    },
    {
      "packet_id": "299",
      "received_time": 1669300225215
    }
  ]
}